<?xml version="1.0" encoding="UTF-8" ?><student_info><function_name>到課統計 </function_name><query_role>匯出的身分： 正式生</query_role><items><item type="title"><serial>序號</serial><account>帳號 </account><realname>姓名  </realname><login_times>登入次數 </login_times><last_login>最近一次登入時間 </last_login><studying_times>上課次數 </studying_times><last_studying>最近一次上課時間 </last_studying><post_times>張貼篇數 </post_times><discuss_times>討論次數 </discuss_times><read_time>閱讀時數 </read_time><read_pages>閱讀頁數 </read_pages></item><item><serial>1</serial><account>C111133307</account><realname>陳彥蓁</realname><login_times>546</login_times><last_login>2026-04-26 17:03:05</last_login><studying_times>8</studying_times><last_studying>2026-04-17 15:19:34</last_studying><post_times>0</post_times><discuss_times>0</discuss_times><read_time>02:25:24</read_time><read_pages>9</read_pages></item><item><serial>2</serial><account>C113118138</account><realname>陳品旭</realname><login_times>344</login_times><last_login>2026-04-27 15:53:32</last_login><studying_times>5</studying_times><last_studying>2026-04-17 15:43:53</last_studying><post_times>0</post_times><discuss_times>0</discuss_times><read_time>01:51:24</read_time><read_pages>5</read_pages></item><item><serial>3</serial><account>C113118207</account><realname>顏仕祁</realname><login_times>501</login_times><last_login>2026-04-26 15:04:48</last_login><studying_times>16</studying_times><last_studying>2026-04-17 15:19:47</last_studying><post_times>0</post_times><discuss_times>0</discuss_times><read_time>02:24:33</read_time><read_pages>4</read_pages></item><item><serial>4</serial><account>C113118234</account><realname>呂孟澤</realname><login_times>429</login_times><last_login>2026-04-26 19:12:01</last_login><studying_times>10</studying_times><last_studying>2026-04-17 15:20:55</last_studying><post_times>0</post_times><discuss_times>0</discuss_times><read_time>02:25:36</read_time><read_pages>8</read_pages></item><item><serial>5</serial><account>C113118235</account><realname>施誠軒</realname><login_times>302</login_times><last_login>2026-04-27 16:27:40</last_login><studying_times>7</studying_times><last_studying>2026-04-17 15:20:06</last_studying><post_times>0</post_times><discuss_times>0</discuss_times><read_time>02:24:29</read_time><read_pages>7</read_pages></item><item><serial>6</serial><account>C112118111</account><realname>鍾昌錦</realname><login_times>568</login_times><last_login>2026-04-26 15:15:09</last_login><studying_times>3</studying_times><last_studying>2026-04-17 15:25:57</last_studying><post_times>0</post_times><discuss_times>0</discuss_times><read_time>01:27:35</read_time><read_pages>3</read_pages></item><item><serial>7</serial><account>C112118113</account><realname>黃俊霖</realname><login_times>1073</login_times><last_login>2026-04-26 17:38:28</last_login><studying_times>9</studying_times><last_studying>2026-04-17 15:19:45</last_studying><post_times>0</post_times><discuss_times>0</discuss_times><read_time>01:38:29</read_time><read_pages>10</read_pages></item><item><serial>8</serial><account>C112118206</account><realname>陳文嬡</realname><login_times>603</login_times><last_login>2026-04-23 14:50:45</last_login><studying_times>11</studying_times><last_studying>2026-04-17 15:19:52</last_studying><post_times>0</post_times><discuss_times>0</discuss_times><read_time>02:35:03</read_time><read_pages>6</read_pages></item><item><serial>9</serial><account>C112118245</account><realname>蘇子凡</realname><login_times>451</login_times><last_login>2026-04-21 11:54:37</last_login><studying_times>4</studying_times><last_studying>2026-04-17 15:21:04</last_studying><post_times>0</post_times><discuss_times>0</discuss_times><read_time>01:18:35</read_time><read_pages>3</read_pages></item><item><serial>10</serial><account>C111118128</account><realname>張任沂</realname><login_times>983</login_times><last_login>2026-04-24 04:38:29</last_login><studying_times>2</studying_times><last_studying>2026-04-17 15:19:57</last_studying><post_times>0</post_times><discuss_times>0</discuss_times><read_time>02:05:50</read_time><read_pages>3</read_pages></item><item><serial>11</serial><account>F114119117</account><realname>陳家豪</realname><login_times>199</login_times><last_login>2026-04-26 21:24:45</last_login><studying_times>7</studying_times><last_studying>2026-04-17 15:20:35</last_studying><post_times>0</post_times><discuss_times>0</discuss_times><read_time>02:17:45</read_time><read_pages>5</read_pages></item><item><serial>12</serial><account>F114119127</account><realname>鄭雨虹</realname><login_times>165</login_times><last_login>2026-04-26 14:58:59</last_login><studying_times>5</studying_times><last_studying>2026-04-26 14:59:41</last_studying><post_times>0</post_times><discuss_times>0</discuss_times><read_time>02:26:08</read_time><read_pages>4</read_pages></item><item><serial>13</serial><account>F114119128</account><realname>黃琪云</realname><login_times>53</login_times><last_login>2026-04-23 02:12:52</last_login><studying_times>3</studying_times><last_studying>2026-04-17 15:19:51</last_studying><post_times>0</post_times><discuss_times>0</discuss_times><read_time>02:25:25</read_time><read_pages>6</read_pages></item><item><serial>14</serial><account>F114119134</account><realname>翁嘉駿</realname><login_times>163</login_times><last_login>2026-04-23 23:55:58</last_login><studying_times>12</studying_times><last_studying>2026-04-23 21:04:35</last_studying><post_times>0</post_times><discuss_times>0</discuss_times><read_time>05:01:06</read_time><read_pages>6</read_pages></item><item><serial>15</serial><account>F114119135</account><realname>黃宇睦</realname><login_times>38</login_times><last_login>2026-04-24 10:01:48</last_login><studying_times>39</studying_times><last_studying>2026-04-17 15:50:03</last_studying><post_times>0</post_times><discuss_times>0</discuss_times><read_time>02:38:29</read_time><read_pages>30</read_pages></item><item><serial>16</serial><account>F111119122</account><realname>陳柏勳</realname><login_times>132</login_times><last_login>2026-03-31 21:11:50</last_login><studying_times>6</studying_times><last_studying>2026-03-27 15:57:38</last_studying><post_times>0</post_times><discuss_times>0</discuss_times><read_time>0</read_time><read_pages>0</read_pages></item><item><serial>17</serial><account>F114118103</account><realname>陳佳維</realname><login_times>177</login_times><last_login>2026-04-24 08:31:55</last_login><studying_times>6</studying_times><last_studying>2026-04-24 08:32:00</last_studying><post_times>0</post_times><discuss_times>0</discuss_times><read_time>02:49:34</read_time><read_pages>6</read_pages></item><item><serial>18</serial><account>F114118116</account><realname>簡婉庭</realname><login_times>119</login_times><last_login>2026-03-15 20:30:27</last_login><studying_times>0</studying_times><last_studying></last_studying><post_times>0</post_times><discuss_times>0</discuss_times><read_time>0</read_time><read_pages>0</read_pages></item><item><serial>19</serial><account>F114118117</account><realname>余欣恬</realname><login_times>188</login_times><last_login>2026-04-22 18:15:31</last_login><studying_times>7</studying_times><last_studying>2026-04-22 18:16:35</last_studying><post_times>0</post_times><discuss_times>0</discuss_times><read_time>00:00:04</read_time><read_pages>1</read_pages></item><item><serial>20</serial><account>F114118119</account><realname>曾子恩</realname><login_times>120</login_times><last_login>2026-04-27 17:36:29</last_login><studying_times>14</studying_times><last_studying>2026-04-17 15:18:51</last_studying><post_times>1</post_times><discuss_times>0</discuss_times><read_time>03:19:39</read_time><read_pages>19</read_pages></item><item><serial>21</serial><account>F114118124</account><realname>劉宇軒</realname><login_times>229</login_times><last_login>2026-04-19 21:51:34</last_login><studying_times>1</studying_times><last_studying>2026-03-15 16:26:26</last_studying><post_times>0</post_times><discuss_times>0</discuss_times><read_time>0</read_time><read_pages>0</read_pages></item><item><serial>22</serial><account>F114118126</account><realname>陳亭邑</realname><login_times>76</login_times><last_login>2026-04-27 13:48:47</last_login><studying_times>7</studying_times><last_studying>2026-04-17 15:41:20</last_studying><post_times>0</post_times><discuss_times>0</discuss_times><read_time>02:00:43</read_time><read_pages>5</read_pages></item><item><serial>23</serial><account>F114118128</account><realname>翁楨惟</realname><login_times>138</login_times><last_login>2026-04-23 19:40:25</last_login><studying_times>4</studying_times><last_studying>2026-04-23 19:39:22</last_studying><post_times>0</post_times><discuss_times>0</discuss_times><read_time>00:01:32</read_time><read_pages>2</read_pages></item><item><serial>24</serial><account>F113118121</account><realname>夏辰旭</realname><login_times>200</login_times><last_login>2026-04-27 09:59:03</last_login><studying_times>1</studying_times><last_studying>2026-03-20 16:05:14</last_studying><post_times>0</post_times><discuss_times>0</discuss_times><read_time>0</read_time><read_pages>0</read_pages></item><item><serial>25</serial><account>F113118122</account><realname>林妤珊</realname><login_times>340</login_times><last_login>2026-01-15 21:18:26</last_login><studying_times>0</studying_times><last_studying></last_studying><post_times>0</post_times><discuss_times>0</discuss_times><read_time>0</read_time><read_pages>0</read_pages></item><item><serial>26</serial><account>F113118132</account><realname>劉立凱</realname><login_times>132</login_times><last_login>2026-03-17 13:38:58</last_login><studying_times>2</studying_times><last_studying>2026-03-10 16:32:52</last_studying><post_times>0</post_times><discuss_times>0</discuss_times><read_time>0</read_time><read_pages>0</read_pages></item></items></student_info>